{
    "person":[
        {
            "illName":"aaaaaaaa",
            "Comments":[
                {
                    "DoctorName":"Alaa",
                    "Comment":"comment comment comment comment comment comment "
                },
                {
                    "DoctorName":"Alaa",
                    "Comment":"comment comment comment comment comment comment "
                },
                {
                    "DoctorName":"Alaa",
                    "Comment":"comment comment comment comment comment comment "
                },
                {
                    "DoctorName":"Alaa",
                    "Comment":"comment comment comment comment comment comment "
                }
            ]
        },
        {
            "illName":"aaaaaaaa",
            "Comments":[
                {
                    "DoctorName":"Alaa",
                    "Comment":"comment comment comment comment comment comment "
                },
                {
                    "DoctorName":"Alaa",
                    "Comment":"comment comment comment comment comment comment "
                },
                {
                    "DoctorName":"Alaa",
                    "Comment":"comment comment comment comment comment comment "
                },
                {
                    "DoctorName":"Alaa",
                    "Comment":"comment comment comment comment comment comment "
                }
            ]
        },
        {
            "illName":"aaaaaaaa",
            "Comments":[
                {
                    "DoctorName":"Alaa",
                    "Comment":"comment comment comment comment comment comment "
                },
                {
                    "DoctorName":"Alaa",
                    "Comment":"comment comment comment comment comment comment "
                },
                {
                    "DoctorName":"Alaa",
                    "Comment":"comment comment comment comment comment comment "
                },
                {
                    "DoctorName":"Alaa",
                    "Comment":"comment comment comment comment comment comment "
                }
            ]
        }
]
}